kubetools/__init__.py
kubetools/config.py
kubetools/constants.py
kubetools/exceptions.py
kubetools/log.py
kubetools/main.py
kubetools/settings.py
kubetools/cli/__init__.py
kubetools/cli/__main__.py
kubetools/cli/deploy.py
kubetools/cli/generate_config.py
kubetools/cli/git_utils.py
kubetools/cli/push_image.py
kubetools/cli/server_util.py
kubetools/cli/show.py
kubetools/deploy/__init__.py
kubetools/deploy/build.py
kubetools/deploy/image.py
kubetools/deploy/util.py
kubetools/deploy/commands/__init__.py
kubetools/deploy/commands/cleanup.py
kubetools/deploy/commands/deploy.py
kubetools/deploy/commands/remove.py
kubetools/deploy/commands/restart.py
kubetools/dev/__init__.py
kubetools/dev/__main__.py
kubetools/dev/backend.py
kubetools/dev/container.py
kubetools/dev/environment.py
kubetools/dev/logs.py
kubetools/dev/process_util.py
kubetools/dev/scripts.py
kubetools/dev/backends/__init__.py
kubetools/dev/backends/docker_compose/__init__.py
kubetools/dev/backends/docker_compose/config.py
kubetools/dev/backends/docker_compose/docker_util.py
kubetools/kubernetes/__init__.py
kubetools/kubernetes/api.py
kubetools/kubernetes/config/__init__.py
kubetools/kubernetes/config/container.py
kubetools/kubernetes/config/cronjob.py
kubetools/kubernetes/config/deployment.py
kubetools/kubernetes/config/job.py
kubetools/kubernetes/config/namespace.py
kubetools/kubernetes/config/service.py
kubetools/kubernetes/config/util.py
kubetools/kubernetes/config/volume.py
tests/__init__.py
tests/conftest.py
tests/test_build_compose_command.py
tests/test_config_generation.py
tests/test_make_job_config.py
kubetools-13.14.1.dist-info/LICENSE.md
kubetools-13.14.1.dist-info/METADATA
kubetools-13.14.1.dist-info/WHEEL
kubetools-13.14.1.dist-info/entry_points.txt
kubetools-13.14.1.dist-info/top_level.txt
kubetools-13.14.1.dist-info/RECORD
