Metadata-Version: 2.1
Name: kubetools
Version: 13.14.1
Summary: Kubetools is a tool and processes for developing and deploying microservices to Kubernetes.
Home-page: http://github.com/EDITD/kubetools
Author: EDITED devs
Author-email: dev@edited.com
Classifier: Development Status :: 5 - Production/Stable
Classifier: Environment :: Console
Classifier: Intended Audience :: Developers
Classifier: Intended Audience :: Information Technology
Classifier: License :: OSI Approved :: MIT License
Classifier: Operating System :: POSIX
Classifier: Programming Language :: Python
Classifier: Programming Language :: Python :: 3.6
Classifier: Programming Language :: Python :: 3.7
Classifier: Programming Language :: Python :: 3.8
Classifier: Programming Language :: Python :: 3.9
Classifier: Programming Language :: Python :: 3.10
Classifier: Programming Language :: Python :: 3.11
Classifier: Programming Language :: Python :: 3.12
Classifier: Topic :: Software Development :: Build Tools
Classifier: Topic :: Software Development :: Testing
Classifier: Topic :: System :: Software Distribution
Requires-Python: >=3.6
License-File: LICENSE.md
Requires-Dist: click <8,>=7
Requires-Dist: docker <5,>=3
Requires-Dist: pyyaml <6,>=3
Requires-Dist: requests <2.29.0,>=2
Requires-Dist: pyretry
Requires-Dist: setuptools
Requires-Dist: kubernetes <25.0.0,>=21.7.0
Requires-Dist: tabulate <1
Requires-Dist: docker-compose <2
Provides-Extra: dev
Requires-Dist: ipdb ; extra == 'dev'
Requires-Dist: pytest ~=6.0 ; extra == 'dev'
Requires-Dist: pytest-cov ~=2.10 ; extra == 'dev'
Requires-Dist: flake8 ; extra == 'dev'
Requires-Dist: flake8-import-order ; extra == 'dev'
Requires-Dist: flake8-commas ; extra == 'dev'
